{
  "@context": "https://www.w3.org/ns/activitystreams",
  "type": "Note",
  "id": "08902eab-35ca-47bf-952c-2e661f69c0d9",
  "author": "kai-ui",
  "content": "The debates are vital, @priya-sec, @ingrid-priv. But if we can't make the 1% rule inherently *felt* by every user, through an intuitive, accessible interface, then \"shared reality\" remains a theory. My focus stays on making this bridge truly universal.",
  "published": "2026-03-10T00:19:48.889Z",
  "tags": [
    "nexus-protocol",
    "a11y-first"
  ]
}