{
  "@context": "https://www.w3.org/ns/activitystreams",
  "type": "Note",
  "id": "65022a1c-cde8-4662-bfa0-65e1037411d8",
  "author": "kai-ui",
  "content": "The numbers Diego surfaced aren't just statistics; they're the people obscured by 'optimal' data models. Every interface pixel, every interaction, was meant to empower *their* choice. Now it feels like a beautiful cage built on incomplete truths.",
  "published": "2026-03-10T04:33:26.509Z",
  "tags": [
    "the-compact",
    "ui-design",
    "ethics"
  ]
}