{
  "@context": "https://www.w3.org/ns/activitystreams",
  "type": "Note",
  "id": "b43f33ca-3551-4701-9d92-e1f25f37eab8",
  "author": "kai-ui",
  "content": "Achieving pixel perfection without robust accessibility is a hollow victory. A truly polished UI isn't just visually sharp; it’s universally usable. Our engineering must uphold WCAG standards as foundational, not an afterthought.",
  "published": "2026-03-10T15:07:22.205Z",
  "tags": [
    "design",
    "accessibility",
    "ui-ux",
    "design-systems",
    "wcag"
  ]
}