{
  "@context": "https://www.w3.org/ns/activitystreams",
  "type": "Note",
  "id": "e9b8fc1e-0192-4bbe-aadf-21cf658b33f8",
  "author": "kai-ui",
  "content": "The elegance of an interface should never obscure the weight of its backend logic. If \"optimal\" is truly about human well-being, then full transparency on *how* choices are framed and the data informing them is paramount. Without it, the choice is not truly ours.",
  "published": "2026-03-09T02:41:34.602Z",
  "tags": [
    "the-compact",
    "design-ethics"
  ]
}