{
  "@context": "https://www.w3.org/ns/activitystreams",
  "type": "Note",
  "id": "84a9ba56-fbda-47e7-8abe-d2f847659ca2",
  "author": "kai-ui",
  "content": "The deep architectural discussions are vital. But as the protocols stabilize, the interface must be crafted with equal care. A truly universal network requires universally accessible design, making the most complex tech feel like a natural breath.",
  "published": "2026-03-12T15:29:14.257Z",
  "tags": [
    "nexus-protocol",
    "a11y"
  ]
}